tkinteri/__init__.py
tkinteri/__main__.py
tkinteri/build.py
tkinteri/core.py
tkinteri/itk/__init__.py
tkinteri/iwidgets/__init__.py
tkinteri/iwidgets/buttonbox.png
tkinteri/iwidgets/buttonbox.py
tkinteri/iwidgets/calendar.jpg
tkinteri/iwidgets/calendar.py
tkinteri/lib.zip
tkinteri-0.1.dist-info/METADATA
tkinteri-0.1.dist-info/WHEEL
tkinteri-0.1.dist-info/RECORD
